[{"id":1,"name":"Bitcoin","symbol":"BTC","slug":"bitcoin","num_market_pairs":7692,"date_added":"2013-04-28T00:00:00.000Z","tags":["mineable"],"max_supply":21000000,"circulating_supply":18313825,"total_supply":18313825,"platform":null,"cmc_rank":1,"last_updated":"2020-04-09T09:35:44.000Z","quote":{"USD":{"price":7306.16436659,"volume_24h":34339298051.2615,"percent_change_1h":-0.120564,"percent_change_24h":0.23891,"percent_change_7d":9.84901,"market_cap":133803815630.9651,"last_updated":"2020-04-09T09:35:44.000Z"}},"price":7306.16436659,"volume_24h":34339298051.2615,"percent_change_1h":-0.120564,"percent_change_24h":0.23891,"percent_change_7d":9.84901,"market_cap":133803815630.9651,"image":"https://shapeshift.io/images/coins/bitcoin.png"},{"id":1027,"name":"Ethereum","symbol":"ETH","slug":"ethereum","num_market_pairs":5057,"date_added":"2015-08-07T00:00:00.000Z","tags":["mineable"],"max_supply":null,"circulating_supply":110444419.374,"total_supply":110444419.374,"platform":null,"cmc_rank":2,"last_updated":"2020-04-09T09:35:31.000Z","quote":{"USD":{"price":171.800683619,"volume_24h":14842582853.5105,"percent_change_1h":-0.231917,"percent_change_24h":1.41029,"percent_change_7d":24.8155,"market_cap":18974426750.356728,"last_updated":"2020-04-09T09:35:31.000Z"}},"price":171.800683619,"volume_24h":14842582853.5105,"percent_change_1h":-0.231917,"percent_change_24h":1.41029,"percent_change_7d":24.8155,"market_cap":18974426750.356728,"image":"https://shapeshift.io/images/coins/ether.png"},{"id":52,"name":"XRP","symbol":"XRP","slug":"xrp","num_market_pairs":513,"date_added":"2013-08-04T00:00:00.000Z","tags":[],"max_supply":100000000000,"circulating_supply":43978966311,"total_supply":99991020177,"platform":null,"cmc_rank":3,"last_updated":"2020-04-09T09:35:08.000Z","quote":{"USD":{"price":0.199287859896,"volume_24h":1845108869.28392,"percent_change_1h":-0.183706,"percent_change_24h":0.416517,"percent_change_7d":12.9216,"market_cap":8764474076.557472,"last_updated":"2020-04-09T09:35:08.000Z"}},"price":0.199287859896,"volume_24h":1845108869.28392,"percent_change_1h":-0.183706,"percent_change_24h":0.416517,"percent_change_7d":12.9216,"market_cap":8764474076.557472,"image":"https://shapeshift.io/images/coins/ripple.png"},{"id":825,"name":"Tether","symbol":"USDT","slug":"tether","num_market_pairs":4381,"date_added":"2015-02-25T00:00:00.000Z","tags":[],"max_supply":null,"circulating_supply":6361032509,"total_supply":6998318752.17,"platform":{"id":83,"name":"Omni","symbol":"OMNI","slug":"omni","token_address":"31"},"cmc_rank":4,"last_updated":"2020-04-09T09:35:30.000Z","quote":{"USD":{"price":0.998273552543,"volume_24h":44361311975.0889,"percent_change_1h":-0.0219546,"percent_change_24h":-0.132696,"percent_change_7d":-0.46386,"market_cap":6350050520.600943,"last_updated":"2020-04-09T09:35:30.000Z"}},"price":0.998273552543,"volume_24h":44361311975.0889,"percent_change_1h":-0.0219546,"percent_change_24h":-0.132696,"percent_change_7d":-0.46386,"market_cap":6350050520.600943,"image":"https://shapeshift.io/images/coins/tether.png"},{"id":1831,"name":"Bitcoin Cash","symbol":"BCH","slug":"bitcoin-cash","num_market_pairs":458,"date_added":"2017-07-23T00:00:00.000Z","tags":["mineable"],"max_supply":21000000,"circulating_supply":18375443.75,"total_supply":18375443.75,"platform":null,"cmc_rank":5,"last_updated":"2020-04-09T09:35:08.000Z","quote":{"USD":{"price":264.798104756,"volume_24h":4679612110.57032,"percent_change_1h":-0.241948,"percent_change_24h":-3.10523,"percent_change_7d":16.9198,"market_cap":4865782679.050486,"last_updated":"2020-04-09T09:35:08.000Z"}},"price":264.798104756,"volume_24h":4679612110.57032,"percent_change_1h":-0.241948,"percent_change_24h":-3.10523,"percent_change_7d":16.9198,"market_cap":4865782679.050486,"image":"https://shapeshift.io/images/coins/bitcoincash.png"},{"id":2,"name":"Litecoin","symbol":"LTC","slug":"litecoin","num_market_pairs":576,"date_added":"2013-04-28T00:00:00.000Z","tags":["mineable"],"max_supply":84000000,"circulating_supply":64469889.9924873,"total_supply":64469889.9924873,"platform":null,"cmc_rank":7,"last_updated":"2020-04-09T09:35:09.000Z","quote":{"USD":{"price":46.0761901086,"volume_24h":3540339140.15254,"percent_change_1h":-0.25497,"percent_change_24h":0.12023,"percent_change_7d":16.1797,"market_cap":2970526907.5743732,"last_updated":"2020-04-09T09:35:09.000Z"}},"price":46.0761901086,"volume_24h":3540339140.15254,"percent_change_1h":-0.25497,"percent_change_24h":0.12023,"percent_change_7d":16.1797,"market_cap":2970526907.5743732,"image":"https://shapeshift.io/images/coins/litecoin.png"},{"id":1765,"name":"EOS","symbol":"EOS","slug":"eos","num_market_pairs":376,"date_added":"2017-07-01T00:00:00.000Z","tags":[],"max_supply":null,"circulating_supply":921637994.785,"total_supply":1018338006.5845,"platform":null,"cmc_rank":8,"last_updated":"2020-04-09T09:35:07.000Z","quote":{"USD":{"price":2.73170393257,"volume_24h":3011018742.31606,"percent_change_1h":-0.202668,"percent_change_24h":0.537958,"percent_change_7d":19.7275,"market_cap":2517642134.7601132,"last_updated":"2020-04-09T09:35:07.000Z"}},"price":2.73170393257,"volume_24h":3011018742.31606,"percent_change_1h":-0.202668,"percent_change_24h":0.537958,"percent_change_7d":19.7275,"market_cap":2517642134.7601132,"image":"https://shapeshift.io/images/coins/eos.png"},{"id":1839,"name":"Binance Coin","symbol":"BNB","slug":"binance-coin","num_market_pairs":296,"date_added":"2017-07-25T00:00:00.000Z","tags":[],"max_supply":187536713,"circulating_supply":155536713,"total_supply":187536713,"platform":null,"cmc_rank":9,"last_updated":"2020-04-09T09:35:07.000Z","quote":{"USD":{"price":15.1445556104,"volume_24h":411889121.129312,"percent_change_1h":0.122288,"percent_change_24h":1.0019,"percent_change_7d":17.9729,"market_cap":2355534399.4873247,"last_updated":"2020-04-09T09:35:07.000Z"}},"price":15.1445556104,"volume_24h":411889121.129312,"percent_change_1h":0.122288,"percent_change_24h":1.0019,"percent_change_7d":17.9729,"market_cap":2355534399.4873247,"image":"https://shapeshift.io/images/coins/binance.png"},{"id":328,"name":"Monero","symbol":"XMR","slug":"monero","num_market_pairs":138,"date_added":"2014-05-21T00:00:00.000Z","tags":["mineable"],"max_supply":null,"circulating_supply":17515897.5532148,"total_supply":17515897.5532148,"platform":null,"cmc_rank":14,"last_updated":"2020-04-09T09:35:05.000Z","quote":{"USD":{"price":57.5842515626,"volume_24h":91264601.588217,"percent_change_1h":0.17714,"percent_change_24h":0.931755,"percent_change_7d":18.0635,"market_cap":1008639851.0490509,"last_updated":"2020-04-09T09:35:05.000Z"}},"price":57.5842515626,"volume_24h":91264601.588217,"percent_change_1h":0.17714,"percent_change_24h":0.931755,"percent_change_7d":18.0635,"market_cap":1008639851.0490509,"image":"https://shapeshift.io/images/coins/monero.png"},{"id":131,"name":"Dash","symbol":"DASH","slug":"dash","num_market_pairs":285,"date_added":"2014-02-14T00:00:00.000Z","tags":["mineable"],"max_supply":18900000,"circulating_supply":9429742.67817075,"total_supply":9429742.67817075,"platform":null,"cmc_rank":19,"last_updated":"2020-04-09T09:35:05.000Z","quote":{"USD":{"price":78.460557154,"volume_24h":779056503.014396,"percent_change_1h":1.56156,"percent_change_24h":4.784,"percent_change_7d":19.1751,"market_cap":739862864.3481292,"last_updated":"2020-04-09T09:35:05.000Z"}},"price":78.460557154,"volume_24h":779056503.014396,"percent_change_1h":1.56156,"percent_change_24h":4.784,"percent_change_7d":19.1751,"market_cap":739862864.3481292,"image":"https://shapeshift.io/images/coins/dash.png"},{"id":3408,"name":"USD Coin","symbol":"USDC","slug":"usd-coin","num_market_pairs":218,"date_added":"2018-10-08T00:00:00.000Z","tags":[],"max_supply":null,"circulating_supply":709773774.13567,"total_supply":715785691.31,"platform":{"id":1027,"name":"Ethereum","symbol":"ETH","slug":"ethereum","token_address":"0xa0b86991c6218b36c1d19d4a2e9eb0ce3606eb48"},"cmc_rank":20,"last_updated":"2020-04-09T09:35:12.000Z","quote":{"USD":{"price":0.996464777539,"volume_24h":763394912.57957,"percent_change_1h":0.00437137,"percent_change_24h":-0.171169,"percent_change_7d":-0.33126,"market_cap":707264565.9471167,"last_updated":"2020-04-09T09:35:12.000Z"}},"price":0.996464777539,"volume_24h":763394912.57957,"percent_change_1h":0.00437137,"percent_change_24h":-0.171169,"percent_change_7d":-0.33126,"market_cap":707264565.9471167,"image":"https://shapeshift.io/images/coins/usdcoin.png"},{"id":1321,"name":"Ethereum Classic","symbol":"ETC","slug":"ethereum-classic","num_market_pairs":240,"date_added":"2016-07-24T00:00:00.000Z","tags":["mineable"],"max_supply":210000000,"circulating_supply":116313299,"total_supply":116313299,"platform":null,"cmc_rank":21,"last_updated":"2020-04-09T09:35:06.000Z","quote":{"USD":{"price":5.79625643075,"volume_24h":1816618332.2669,"percent_change_1h":-0.136142,"percent_change_24h":1.47378,"percent_change_7d":14.8887,"market_cap":674181707.3104975,"last_updated":"2020-04-09T09:35:06.000Z"}},"price":5.79625643075,"volume_24h":1816618332.2669,"percent_change_1h":-0.136142,"percent_change_24h":1.47378,"percent_change_7d":14.8887,"market_cap":674181707.3104975,"image":"https://shapeshift.io/images/coins/etherclassic.png"},{"id":1376,"name":"Neo","symbol":"NEO","slug":"neo","num_market_pairs":224,"date_added":"2016-09-08T00:00:00.000Z","tags":[],"max_supply":100000000,"circulating_supply":70538831,"total_supply":100000000,"platform":null,"cmc_rank":22,"last_updated":"2020-04-09T09:35:06.000Z","quote":{"USD":{"price":8.07721063758,"volume_24h":368499339.117982,"percent_change_1h":0.835102,"percent_change_24h":2.98364,"percent_change_7d":17.4598,"market_cap":569756996.1156579,"last_updated":"2020-04-09T09:35:06.000Z"}},"price":8.07721063758,"volume_24h":368499339.117982,"percent_change_1h":0.835102,"percent_change_24h":2.98364,"percent_change_7d":17.4598,"market_cap":569756996.1156579,"image":"https://shapeshift.io/images/coins/neo.png"},{"id":3794,"name":"Cosmos","symbol":"ATOM","slug":"cosmos","num_market_pairs":120,"date_added":"2019-03-14T00:00:00.000Z","tags":[],"max_supply":null,"circulating_supply":190688439.2,"total_supply":237928230.821588,"platform":null,"cmc_rank":24,"last_updated":"2020-04-09T09:35:12.000Z","quote":{"USD":{"price":2.53095868498,"volume_24h":160723673.232686,"percent_change_1h":2.87382,"percent_change_24h":7.67811,"percent_change_7d":27.2051,"market_cap":482624561.3185206,"last_updated":"2020-04-09T09:35:12.000Z"}},"price":2.53095868498,"volume_24h":160723673.232686,"percent_change_1h":2.87382,"percent_change_24h":7.67811,"percent_change_7d":27.2051,"market_cap":482624561.3185206,"image":"https://shapeshift.io/images/coins/atom.png"},{"id":1437,"name":"Zcash","symbol":"ZEC","slug":"zcash","num_market_pairs":221,"date_added":"2016-10-29T00:00:00.000Z","tags":["mineable"],"max_supply":21000000,"circulating_supply":9757143.75,"total_supply":9757143.75,"platform":null,"cmc_rank":26,"last_updated":"2020-04-09T09:35:06.000Z","quote":{"USD":{"price":39.8209865138,"volume_24h":453288202.15734,"percent_change_1h":-0.995487,"percent_change_24h":6.68077,"percent_change_7d":26.2389,"market_cap":388539089.68195796,"last_updated":"2020-04-09T09:35:06.000Z"}},"price":39.8209865138,"volume_24h":453288202.15734,"percent_change_1h":-0.995487,"percent_change_24h":6.68077,"percent_change_7d":26.2389,"market_cap":388539089.68195796,"image":"https://shapeshift.io/images/coins/zcash.png"},{"id":1518,"name":"Maker","symbol":"MKR","slug":"maker","num_market_pairs":59,"date_added":"2017-01-29T00:00:00.000Z","tags":[],"max_supply":null,"circulating_supply":1005888.33337068,"total_supply":1005888.33337068,"platform":{"id":1027,"name":"Ethereum","symbol":"ETH","slug":"ethereum","token_address":"0x9f8f72aa9304c8b593d555f12ef6589cc3a579a2"},"cmc_rank":28,"last_updated":"2020-04-09T09:35:05.000Z","quote":{"USD":{"price":339.778057612,"volume_24h":3119501.13950048,"percent_change_1h":-0.232565,"percent_change_24h":0.1686,"percent_change_7d":13.6708,"market_cap":341778784.08726156,"last_updated":"2020-04-09T09:35:05.000Z"}},"price":339.778057612,"volume_24h":3119501.13950048,"percent_change_1h":-0.232565,"percent_change_24h":0.1686,"percent_change_7d":13.6708,"market_cap":341778784.08726156,"image":"https://shapeshift.io/images/coins/maker.png"},{"id":1697,"name":"Basic Attention Token","symbol":"BAT","slug":"basic-attention-token","num_market_pairs":168,"date_added":"2017-06-01T00:00:00.000Z","tags":[],"max_supply":null,"circulating_supply":1455992563.5663,"total_supply":1500000000,"platform":{"id":1027,"name":"Ethereum","symbol":"ETH","slug":"ethereum","token_address":"0x0d8775f648430679a709e98d2b0cb6250d2887ef"},"cmc_rank":32,"last_updated":"2020-04-09T09:35:06.000Z","quote":{"USD":{"price":0.175390364208,"volume_24h":120593269.053046,"percent_change_1h":-0.098697,"percent_change_24h":5.50006,"percent_change_7d":21.0686,"market_cap":255367066.00803292,"last_updated":"2020-04-09T09:35:06.000Z"}},"price":0.175390364208,"volume_24h":120593269.053046,"percent_change_1h":-0.098697,"percent_change_24h":5.50006,"percent_change_7d":21.0686,"market_cap":255367066.00803292,"image":"https://shapeshift.io/images/coins/basicattentiontoken.png"},{"id":74,"name":"Dogecoin","symbol":"DOGE","slug":"dogecoin","num_market_pairs":230,"date_added":"2013-12-15T00:00:00.000Z","tags":["mineable"],"max_supply":null,"circulating_supply":124068290427.312,"total_supply":124068290427.312,"platform":null,"cmc_rank":33,"last_updated":"2020-04-09T09:35:05.000Z","quote":{"USD":{"price":0.00200698503105,"volume_24h":111120789.247066,"percent_change_1h":0.0196024,"percent_change_24h":-0.0317712,"percent_change_7d":7.45408,"market_cap":249003201.71557918,"last_updated":"2020-04-09T09:35:05.000Z"}},"price":0.00200698503105,"volume_24h":111120789.247066,"percent_change_1h":0.0196024,"percent_change_24h":-0.0317712,"percent_change_7d":7.45408,"market_cap":249003201.71557918,"image":"https://shapeshift.io/images/coins/dogecoin.png"},{"id":3330,"name":"Paxos Standard","symbol":"PAX","slug":"paxos-standard","num_market_pairs":94,"date_added":"2018-09-27T00:00:00.000Z","tags":[],"max_supply":null,"circulating_supply":244951954.494264,"total_supply":249952064.83,"platform":{"id":1027,"name":"Ethereum","symbol":"ETH","slug":"ethereum","token_address":"0x8e870d67f660d95d5be530380d0ec0bd388289e1"},"cmc_rank":34,"last_updated":"2020-04-09T09:35:11.000Z","quote":{"USD":{"price":0.997007542184,"volume_24h":1449136437.70219,"percent_change_1h":0.0245426,"percent_change_24h":-0.14176,"percent_change_7d":-0.315338,"market_cap":244218946.10349318,"last_updated":"2020-04-09T09:35:11.000Z"}},"price":0.997007542184,"volume_24h":1449136437.70219,"percent_change_1h":0.0245426,"percent_change_24h":-0.14176,"percent_change_7d":-0.315338,"market_cap":244218946.10349318,"image":"https://shapeshift.io/images/coins/pax.png"},{"id":1684,"name":"Qtum","symbol":"QTUM","slug":"qtum","num_market_pairs":170,"date_added":"2017-05-24T00:00:00.000Z","tags":[],"max_supply":107822406,"circulating_supply":96514760.0484598,"total_supply":102264780,"platform":null,"cmc_rank":38,"last_updated":"2020-04-09T09:35:06.000Z","quote":{"USD":{"price":1.49912616733,"volume_24h":352303809.861308,"percent_change_1h":-0.077573,"percent_change_24h":5.43444,"percent_change_7d":21.016,"market_cap":144687802.32222214,"last_updated":"2020-04-09T09:35:06.000Z"}},"price":1.49912616733,"volume_24h":352303809.861308,"percent_change_1h":-0.077573,"percent_change_24h":5.43444,"percent_change_7d":21.016,"market_cap":144687802.32222214,"image":"https://shapeshift.io/images/coins/qtum.png"},{"id":1168,"name":"Decred","symbol":"DCR","slug":"decred","num_market_pairs":49,"date_added":"2016-02-10T00:00:00.000Z","tags":["mineable"],"max_supply":21000000,"circulating_supply":10786830.8782284,"total_supply":10786830.8782284,"platform":null,"cmc_rank":40,"last_updated":"2020-04-09T09:35:04.000Z","quote":{"USD":{"price":12.6830673726,"volume_24h":95228838.1052812,"percent_change_1h":0.117501,"percent_change_24h":0.430878,"percent_change_7d":9.90988,"market_cap":136810102.76541284,"last_updated":"2020-04-09T09:35:04.000Z"}},"price":12.6830673726,"volume_24h":95228838.1052812,"percent_change_1h":0.117501,"percent_change_24h":0.430878,"percent_change_7d":9.90988,"market_cap":136810102.76541284,"image":"https://shapeshift.io/images/coins/decred.png"},{"id":2563,"name":"TrueUSD","symbol":"TUSD","slug":"trueusd","num_market_pairs":153,"date_added":"2018-03-06T00:00:00.000Z","tags":[],"max_supply":null,"circulating_supply":137036318.84,"total_supply":137036318.84,"platform":{"id":1027,"name":"Ethereum","symbol":"ETH","slug":"ethereum","token_address":"0x0000000000085d4780B73119b644AE5ecd22b376"},"cmc_rank":41,"last_updated":"2020-04-09T09:35:08.000Z","quote":{"USD":{"price":0.996590128548,"volume_24h":521191221.97675,"percent_change_1h":-0.0186064,"percent_change_24h":-0.138897,"percent_change_7d":-0.398578,"market_cap":136569042.60850033,"last_updated":"2020-04-09T09:35:08.000Z"}},"price":0.996590128548,"volume_24h":521191221.97675,"percent_change_1h":-0.0186064,"percent_change_24h":-0.138897,"percent_change_7d":-0.398578,"market_cap":136569042.60850033,"image":"https://shapeshift.io/images/coins/trueusd.png"},{"id":1214,"name":"Lisk","symbol":"LSK","slug":"lisk","num_market_pairs":58,"date_added":"2016-04-06T00:00:00.000Z","tags":[],"max_supply":null,"circulating_supply":122957553.16859,"total_supply":139043264,"platform":null,"cmc_rank":45,"last_updated":"2020-04-09T09:35:04.000Z","quote":{"USD":{"price":1.04649124784,"volume_24h":3022760.68376825,"percent_change_1h":-0.184398,"percent_change_24h":-1.07333,"percent_change_7d":7.81712,"market_cap":128674003.24675088,"last_updated":"2020-04-09T09:35:04.000Z"}},"price":1.04649124784,"volume_24h":3022760.68376825,"percent_change_1h":-0.184398,"percent_change_24h":-1.07333,"percent_change_7d":7.81712,"market_cap":128674003.24675088,"image":"https://shapeshift.io/images/coins/lisk.png"},{"id":1104,"name":"Augur","symbol":"REP","slug":"augur","num_market_pairs":72,"date_added":"2015-10-27T00:00:00.000Z","tags":[],"max_supply":null,"circulating_supply":11000000,"total_supply":11000000,"platform":{"id":1027,"name":"Ethereum","symbol":"ETH","slug":"ethereum","token_address":"0x1985365e9f78359a9b6ad760e32412f4a445e862"},"cmc_rank":48,"last_updated":"2020-04-09T09:35:04.000Z","quote":{"USD":{"price":10.3150523168,"volume_24h":24954734.3473566,"percent_change_1h":0.386847,"percent_change_24h":-0.92415,"percent_change_7d":1.71227,"market_cap":113465575.4848,"last_updated":"2020-04-09T09:35:04.000Z"}},"price":10.3150523168,"volume_24h":24954734.3473566,"percent_change_1h":0.386847,"percent_change_24h":-0.92415,"percent_change_7d":1.71227,"market_cap":113465575.4848,"image":"https://shapeshift.io/images/coins/augur.png"},{"id":1274,"name":"Waves","symbol":"WAVES","slug":"waves","num_market_pairs":139,"date_added":"2016-06-02T00:00:00.000Z","tags":[],"max_supply":null,"circulating_supply":101619130,"total_supply":101619130,"platform":null,"cmc_rank":50,"last_updated":"2020-04-09T09:35:05.000Z","quote":{"USD":{"price":1.00602338665,"volume_24h":59116818.5028675,"percent_change_1h":0.0144232,"percent_change_24h":0.828915,"percent_change_7d":3.85832,"market_cap":102231221.3110266,"last_updated":"2020-04-09T09:35:05.000Z"}},"price":1.00602338665,"volume_24h":59116818.5028675,"percent_change_1h":0.0144232,"percent_change_24h":0.828915,"percent_change_7d":3.85832,"market_cap":102231221.3110266,"image":"https://shapeshift.io/images/coins/waves.png"},{"id":1808,"name":"OmiseGO","symbol":"OMG","slug":"omisego","num_market_pairs":198,"date_added":"2017-07-14T00:00:00.000Z","tags":[],"max_supply":null,"circulating_supply":140245398.245133,"total_supply":140245398.245133,"platform":{"id":1027,"name":"Ethereum","symbol":"ETH","slug":"ethereum","token_address":"0xd26114cd6EE289AccF82350c8d8487fedB8A0C07"},"cmc_rank":53,"last_updated":"2020-04-09T09:35:06.000Z","quote":{"USD":{"price":0.622484321854,"volume_24h":89884372.665531,"percent_change_1h":0.040179,"percent_change_24h":0.635747,"percent_change_7d":16.1198,"market_cap":87300561.61976579,"last_updated":"2020-04-09T09:35:06.000Z"}},"price":0.622484321854,"volume_24h":89884372.665531,"percent_change_1h":0.040179,"percent_change_24h":0.635747,"percent_change_7d":16.1198,"market_cap":87300561.61976579,"image":"https://shapeshift.io/images/coins/omisego.png"},{"id":109,"name":"DigiByte","symbol":"DGB","slug":"digibyte","num_market_pairs":73,"date_added":"2014-02-06T00:00:00.000Z","tags":["mineable"],"max_supply":21000000000,"circulating_supply":13014225804.8866,"total_supply":13014225804.8866,"platform":null,"cmc_rank":55,"last_updated":"2020-04-09T09:35:04.000Z","quote":{"USD":{"price":0.00650418379823,"volume_24h":1981326.38675741,"percent_change_1h":-0.0148092,"percent_change_24h":2.18998,"percent_change_7d":38.2473,"market_cap":84646916.6266502,"last_updated":"2020-04-09T09:35:04.000Z"}},"price":0.00650418379823,"volume_24h":1981326.38675741,"percent_change_1h":-0.0148092,"percent_change_24h":2.18998,"percent_change_7d":38.2473,"market_cap":84646916.6266502,"image":"https://shapeshift.io/images/coins/digibyte.png"},{"id":4943,"name":"Multi-collateral DAI","symbol":"DAI","slug":"multi-collateral-dai","num_market_pairs":75,"date_added":"2019-11-22T00:00:00.000Z","tags":[],"max_supply":null,"circulating_supply":78903500.5006958,"total_supply":79492523.1428409,"platform":{"id":1027,"name":"Ethereum","symbol":"ETH","slug":"ethereum","token_address":"0x6b175474e89094c44da98b954eedeac495271d0f"},"cmc_rank":58,"last_updated":"2020-04-09T09:35:15.000Z","quote":{"USD":{"price":1.00793052499,"volume_24h":12487633.8287605,"percent_change_1h":-0.45102,"percent_change_24h":-0.876931,"percent_change_7d":-0.916385,"market_cap":79529246.68321504,"last_updated":"2020-04-09T09:35:15.000Z"}},"price":1.00793052499,"volume_24h":12487633.8287605,"percent_change_1h":-0.45102,"percent_change_24h":-0.876931,"percent_change_7d":-0.916385,"market_cap":79529246.68321504,"image":"https://shapeshift.io/images/coins/dai.png"},{"id":1042,"name":"Siacoin","symbol":"SC","slug":"siacoin","num_market_pairs":39,"date_added":"2015-08-26T00:00:00.000Z","tags":["mineable"],"max_supply":null,"circulating_supply":41817047634,"total_supply":41817047634,"platform":null,"cmc_rank":70,"last_updated":"2020-04-09T09:35:04.000Z","quote":{"USD":{"price":0.00145444641529,"volume_24h":492450.255857815,"percent_change_1h":0.327587,"percent_change_24h":-0.881177,"percent_change_7d":13.7047,"market_cap":60820655.02928247,"last_updated":"2020-04-09T09:35:04.000Z"}},"price":0.00145444641529,"volume_24h":492450.255857815,"percent_change_1h":0.327587,"percent_change_24h":-0.881177,"percent_change_7d":13.7047,"market_cap":60820655.02928247,"image":"https://shapeshift.io/images/coins/siacoin.png"},{"id":1759,"name":"Status","symbol":"SNT","slug":"status","num_market_pairs":80,"date_added":"2017-06-28T00:00:00.000Z","tags":[],"max_supply":null,"circulating_supply":3470483788,"total_supply":6804870174,"platform":{"id":1027,"name":"Ethereum","symbol":"ETH","slug":"ethereum","token_address":"0x744d70fdbe2ba4cf95131626614a1763df805b9e"},"cmc_rank":72,"last_updated":"2020-04-09T09:35:05.000Z","quote":{"USD":{"price":0.0169292848721,"volume_24h":14084162.6960494,"percent_change_1h":-0.2145,"percent_change_24h":0.588588,"percent_change_7d":-3.01605,"market_cap":58752808.6910567,"last_updated":"2020-04-09T09:35:05.000Z"}},"price":0.0169292848721,"volume_24h":14084162.6960494,"percent_change_1h":-0.2145,"percent_change_24h":0.588588,"percent_change_7d":-3.01605,"market_cap":58752808.6910567,"image":"https://shapeshift.io/images/coins/status.png"},{"id":1521,"name":"Komodo","symbol":"KMD","slug":"komodo","num_market_pairs":24,"date_added":"2017-02-05T00:00:00.000Z","tags":["mineable"],"max_supply":200000000,"circulating_supply":119146685.99585,"total_supply":119146685.99585,"platform":null,"cmc_rank":76,"last_updated":"2020-04-09T09:35:05.000Z","quote":{"USD":{"price":0.441606631258,"volume_24h":2204986.20927943,"percent_change_1h":-0.443453,"percent_change_24h":-0.435605,"percent_change_7d":19.7659,"market_cap":52615966.62818204,"last_updated":"2020-04-09T09:35:05.000Z"}},"price":0.441606631258,"volume_24h":2204986.20927943,"percent_change_1h":-0.443453,"percent_change_24h":-0.435605,"percent_change_7d":19.7659,"market_cap":52615966.62818204,"image":"https://shapeshift.io/images/coins/komodo.png"},{"id":2469,"name":"Zilliqa","symbol":"ZIL","slug":"zilliqa","num_market_pairs":99,"date_added":"2018-01-25T00:00:00.000Z","tags":["mineable"],"max_supply":21000000000,"circulating_supply":10035464356.0777,"total_supply":13326931509.0777,"platform":null,"cmc_rank":83,"last_updated":"2020-04-09T09:35:07.000Z","quote":{"USD":{"price":0.00463936595686,"volume_24h":8293628.82667486,"percent_change_1h":0.299753,"percent_change_24h":0.527351,"percent_change_7d":17.8223,"market_cap":46558191.69486885,"last_updated":"2020-04-09T09:35:07.000Z"}},"price":0.00463936595686,"volume_24h":8293628.82667486,"percent_change_1h":0.299753,"percent_change_24h":0.527351,"percent_change_7d":17.8223,"market_cap":46558191.69486885,"image":"https://shapeshift.io/images/coins/zilliqa.png"},{"id":1455,"name":"Golem","symbol":"GNT","slug":"golem-network-tokens","num_market_pairs":84,"date_added":"2016-11-18T00:00:00.000Z","tags":[],"max_supply":null,"circulating_supply":980050000,"total_supply":1000000000,"platform":{"id":1027,"name":"Ethereum","symbol":"ETH","slug":"ethereum","token_address":"0xa74476443119A942dE498590Fe1f2454d7D4aC0d"},"cmc_rank":94,"last_updated":"2020-04-09T09:35:05.000Z","quote":{"USD":{"price":0.0379228899319,"volume_24h":4089174.61911964,"percent_change_1h":-0.0325681,"percent_change_24h":2.00102,"percent_change_7d":5.04625,"market_cap":37166328.2777586,"last_updated":"2020-04-09T09:35:05.000Z"}},"price":0.0379228899319,"volume_24h":4089174.61911964,"percent_change_1h":-0.0325681,"percent_change_24h":2.00102,"percent_change_7d":5.04625,"market_cap":37166328.2777586,"image":"https://shapeshift.io/images/coins/golem.png"},{"id":1700,"name":"Aeternity","symbol":"AE","slug":"aeternity","num_market_pairs":43,"date_added":"2017-06-01T00:00:00.000Z","tags":["mineable"],"max_supply":null,"circulating_supply":306733750.5,"total_supply":352554694.49932,"platform":null,"cmc_rank":98,"last_updated":"2020-04-09T09:35:05.000Z","quote":{"USD":{"price":0.112732930913,"volume_24h":7442977.10929543,"percent_change_1h":-0.844544,"percent_change_24h":3.17848,"percent_change_7d":15.3939,"market_cap":34578994.70380188,"last_updated":"2020-04-09T09:35:05.000Z"}},"price":0.112732930913,"volume_24h":7442977.10929543,"percent_change_1h":-0.844544,"percent_change_24h":3.17848,"percent_change_7d":15.3939,"market_cap":34578994.70380188,"image":"https://shapeshift.io/images/coins/aeternity.png"}]